doubanlib/__init__.py
doubanlib/movies.py
doubanlib-0.1.2.dist-info/LICENSE
doubanlib-0.1.2.dist-info/METADATA
doubanlib-0.1.2.dist-info/WHEEL
doubanlib-0.1.2.dist-info/top_level.txt
doubanlib-0.1.2.dist-info/RECORD
