Metadata-Version: 2.1
Name: doubanlib
Version: 0.1.2
Summary: An api tool for DouBan movie
Home-page: https://github.com/xhboke/douban
Author: xhboke
Author-email: 2361903575@qq.com
Project-URL: Bug Reports, https://github.com/xhboke/douban/issues
Keywords: douban,movie
Classifier: Development Status :: 3 - Alpha
Classifier: Intended Audience :: Developers
Classifier: Topic :: Software Development :: Build Tools
Classifier: License :: OSI Approved :: MIT License
Classifier: Programming Language :: Python :: 3
Classifier: Programming Language :: Python :: 3.7
Classifier: Programming Language :: Python :: 3.8
Classifier: Programming Language :: Python :: 3.9
Classifier: Programming Language :: Python :: 3.10
Classifier: Programming Language :: Python :: 3 :: Only
Requires-Python: >=3.7, <4
License-File: LICENSE
Requires-Dist: requests
